setup.py
bin/sync-security-group
ec2_interaccount/__init__.py
ec2_interaccount/sync_security_group.py
ec2_interaccount.egg-info/PKG-INFO
ec2_interaccount.egg-info/SOURCES.txt
ec2_interaccount.egg-info/dependency_links.txt
ec2_interaccount.egg-info/not-zip-safe
ec2_interaccount.egg-info/top_level.txt