Metadata-Version: 1.0
Name: ec2-interaccount
Version: 0.1
Summary: Interaccount EC2 libraries and scripts.
Home-page: http://github.com/benkershner/ec2_interaccount
Author: Ben Kershner
Author-email: ben.kershner@gmail.com
License: MIT
Platform: UNKNOWN
